{"seq_groups": 1, "hash": "c9927850ebc12cd3d8e65e7d3e55e87a", "tri_count": "5671", "events": [{"seq": "8", "frame": "2", "file": "player/playersounds/goose/honk.wav"}, {"seq": "9", "frame": "2", "file": "player/playersounds/goose/honk.wav"}, {"seq": "12", "frame": "2", "file": "player/playersounds/goose/honk2.wav"}, {"seq": "13", "frame": "2", "file": "player/playersounds/goose/honk2.wav"}, {"seq": "14", "frame": "2", "file": "player/playersounds/goose/honk2.wav"}, {"seq": "15", "frame": "2", "file": "player/playersounds/goose/honk2.wav"}, {"seq": "16", "frame": "2", "file": "player/playersounds/goose/honk2.wav"}, {"seq": "17", "frame": "2", "file": "player/playersounds/goose/honk2.wav"}, {"seq": "18", "frame": "2", "file": "player/playersounds/goose/honk2.wav"}, {"seq": "21", "frame": "2", "file": "player/playersounds/goose/honk2.wav"}, {"seq": "24", "frame": "2", "file": "player/playersounds/goose/honk2.wav"}, {"seq": "27", "frame": "2", "file": "player/playersounds/goose/honk2.wav"}, {"seq": "30", "frame": "2", "file": "player/playersounds/goose/honk2.wav"}]}